[
  {
    "_meta": {
      "dataset": "Delhi Traffic Police Challan Schedule",
      "sourceOrganization": "Delhi Traffic Police",
      "sourceUrl": "https://delhitrafficpolice.nic.in/about-us/traffic-fines",
      "reliability": "very-high",
      "notes": "State-specific surcharges and common offenses enforced in Delhi."
    }
  },
  { "offense_code": "DL-101", "description": "Driving without a valid driving license (Sec 3/181 MVA)", "state_code": "NCT", "vehicle_class": "*", "base_fine": 5000, "source_clause": "Sec 3/181 MVA" },
  { "offense_code": "DL-102", "description": "Driving by minor (Sec 4/199A MVA)", "state_code": "NCT", "vehicle_class": "*", "base_fine": 25000, "source_clause": "Sec 4/199A MVA" },
  { "offense_code": "DL-103", "description": "Allowing vehicle to be driven by person without license (Sec 5/180 MVA)", "state_code": "NCT", "vehicle_class": "*", "base_fine": 5000, "source_clause": "Sec 5/180 MVA" },
  { "offense_code": "DL-104", "description": "Driving without a valid Registration Certificate (Sec 39/192 MVA)", "state_code": "NCT", "vehicle_class": "*", "base_fine": 5000, "source_clause": "Sec 39/192 MVA" },
  { "offense_code": "DL-105", "description": "Driving an unregistered vehicle (Sec 39/192 MVA)", "state_code": "NCT", "vehicle_class": "*", "base_fine": 5000, "source_clause": "Sec 39/192 MVA" },
  { "offense_code": "DL-106", "description": "Driving vehicle without a valid Fitness Certificate (Sec 56/192 MVA)", "state_code": "NCT", "vehicle_class": "*", "base_fine": 5000, "source_clause": "Sec 56/192 MVA" },
  { "offense_code": "DL-107", "description": "Driving a transport vehicle without valid Permit (Sec 66/192A MVA)", "state_code": "NCT", "vehicle_class": "HMV", "base_fine": 10000, "source_clause": "Sec 66/192A MVA" },
  { "offense_code": "DL-108", "description": "Driving without valid Insurance (Sec 146/196 MVA)", "state_code": "NCT", "vehicle_class": "*", "base_fine": 2000, "source_clause": "Sec 146/196 MVA" },
  { "offense_code": "DL-109", "description": "Driving without valid PUC (Pollution Under Control) certificate (Sec 190(2) MVA)", "state_code": "NCT", "vehicle_class": "*", "base_fine": 10000, "source_clause": "Sec 190(2) MVA" },
  { "offense_code": "DL-110", "description": "Jumping Red Light (Sec 119/177 MVA & RR 184 MVA)", "state_code": "NCT", "vehicle_class": "*", "base_fine": 1000, "source_clause": "Sec 119/177 MVA" },
  { "offense_code": "DL-111", "description": "Not wearing seat belt while driving (Sec 194B(1) MVA)", "state_code": "NCT", "vehicle_class": "LMV", "base_fine": 1000, "source_clause": "Sec 194B(1) MVA" },
  { "offense_code": "DL-112", "description": "Not wearing seat belt by passenger (Sec 194B(2) MVA)", "state_code": "NCT", "vehicle_class": "LMV", "base_fine": 1000, "source_clause": "Sec 194B(2) MVA" },
  { "offense_code": "DL-113", "description": "Riding two-wheeler without helmet (driver) (Sec 129/194D MVA)", "state_code": "NCT", "vehicle_class": "TWO_WHEELER", "base_fine": 1000, "source_clause": "Sec 129/194D MVA" },
  { "offense_code": "DL-114", "description": "Riding two-wheeler without helmet (pillion) (Sec 129/194D MVA)", "state_code": "NCT", "vehicle_class": "TWO_WHEELER", "base_fine": 1000, "source_clause": "Sec 129/194D MVA" },
  { "offense_code": "DL-115", "description": "Triple riding on two-wheeler (Sec 128/194C MVA)", "state_code": "NCT", "vehicle_class": "TWO_WHEELER", "base_fine": 1000, "source_clause": "Sec 128/194C MVA" },
  { "offense_code": "DL-116", "description": "Over Speeding (LMV) (Sec 112/183(1) MVA)", "state_code": "NCT", "vehicle_class": "LMV", "base_fine": 2000, "source_clause": "Sec 112/183(1) MVA" },
  { "offense_code": "DL-117", "description": "Over Speeding (MPV/HMV) (Sec 112/183(2) MVA)", "state_code": "NCT", "vehicle_class": "HMV", "base_fine": 4000, "source_clause": "Sec 112/183(2) MVA" },
  { "offense_code": "DL-118", "description": "Dangerous Driving / Zig-Zag Driving (Sec 184 MVA)", "state_code": "NCT", "vehicle_class": "*", "base_fine": 5000, "source_clause": "Sec 184 MVA" },
  { "offense_code": "DL-119", "description": "Using mobile phone while driving (Sec 184 MVA)", "state_code": "NCT", "vehicle_class": "*", "base_fine": 5000, "source_clause": "Sec 184 MVA" },
  { "offense_code": "DL-120", "description": "Drunken Driving (Court Challan) (Sec 185 MVA)", "state_code": "NCT", "vehicle_class": "*", "base_fine": 10000, "source_clause": "Sec 185 MVA" },
  { "offense_code": "DL-121", "description": "Defective Number Plate (Sec 50/177 MVA & CMVR 50/51)", "state_code": "NCT", "vehicle_class": "*", "base_fine": 500, "source_clause": "Sec 50/177 MVA" },
  { "offense_code": "DL-122", "description": "Without High Security Registration Plate (HSRP) (Sec 192(1) MVA)", "state_code": "NCT", "vehicle_class": "*", "base_fine": 5000, "source_clause": "Sec 192(1) MVA" },
  { "offense_code": "DL-123", "description": "Tinted Glass (Black Films) (Sec 100(2)/177 MVA & CMVR 100)", "state_code": "NCT", "vehicle_class": "LMV", "base_fine": 500, "source_clause": "Sec 100(2)/177 MVA" },
  { "offense_code": "DL-124", "description": "Improper Parking / Obstructive Parking (Sec 122/177 MVA)", "state_code": "NCT", "vehicle_class": "*", "base_fine": 500, "source_clause": "Sec 122/177 MVA" },
  { "offense_code": "DL-125", "description": "Disobedience of any direction given by Police Officer (Sec 119/179 MVA)", "state_code": "NCT", "vehicle_class": "*", "base_fine": 2000, "source_clause": "Sec 119/179 MVA" },
  { "offense_code": "DL-126", "description": "Carrying load extending beyond the body of the vehicle (Sec 93/177 MVA)", "state_code": "NCT", "vehicle_class": "HMV", "base_fine": 2000, "source_clause": "Sec 93/177 MVA" },
  { "offense_code": "DL-127", "description": "Overloading of Goods Vehicle (Sec 113(3)/194(1) MVA)", "state_code": "NCT", "vehicle_class": "HMV", "base_fine": 20000, "source_clause": "Sec 113(3)/194(1) MVA" },
  { "offense_code": "DL-128", "description": "Carrying passengers in goods vehicle (Sec 66/192A MVA)", "state_code": "NCT", "vehicle_class": "HMV", "base_fine": 10000, "source_clause": "Sec 66/192A MVA" },
  { "offense_code": "DL-129", "description": "No Entry violation (Heavy Vehicles) (Sec 115/194(1) MVA)", "state_code": "NCT", "vehicle_class": "HMV", "base_fine": 20000, "source_clause": "Sec 115/194(1) MVA" },
  { "offense_code": "DL-130", "description": "Pressure Horn / Multi-toned horn (Sec 119(1)/190(2) MVA)", "state_code": "NCT", "vehicle_class": "*", "base_fine": 10000, "source_clause": "Sec 119(1)/190(2) MVA" },
  { "offense_code": "DL-131", "description": "Silencer blast / altered silencer (Sec 190(2) MVA)", "state_code": "NCT", "vehicle_class": "TWO_WHEELER", "base_fine": 10000, "source_clause": "Sec 190(2) MVA" },
  { "offense_code": "DL-132", "description": "Driving Without Indicators / Defective Indicators (Sec 177 MVA)", "state_code": "NCT", "vehicle_class": "*", "base_fine": 500, "source_clause": "Sec 177 MVA" },
  { "offense_code": "DL-133", "description": "Driving Without Rear View Mirror (Sec 177 MVA & CMVR)", "state_code": "NCT", "vehicle_class": "*", "base_fine": 500, "source_clause": "Sec 177 MVA" },
  { "offense_code": "DL-134", "description": "Not giving way to emergency vehicle (Ambulance/Fire) (Sec 194E MVA)", "state_code": "NCT", "vehicle_class": "*", "base_fine": 10000, "source_clause": "Sec 194E MVA" },
  { "offense_code": "DL-135", "description": "Blowing horn in silent zone (Sec 194F MVA)", "state_code": "NCT", "vehicle_class": "*", "base_fine": 1000, "source_clause": "Sec 194F MVA" },
  { "offense_code": "DL-136", "description": "Refusal to ply (Taxis/Autos) (Sec 178 MVA)", "state_code": "NCT", "vehicle_class": "TAXI", "base_fine": 500, "source_clause": "Sec 178 MVA" },
  { "offense_code": "DL-137", "description": "Overcharging fare (Taxis/Autos) (Sec 178 MVA)", "state_code": "NCT", "vehicle_class": "TAXI", "base_fine": 500, "source_clause": "Sec 178 MVA" },
  { "offense_code": "DL-138", "description": "Driving without badge (Commercial drivers) (Sec 177 MVA)", "state_code": "NCT", "vehicle_class": "COMMERCIAL", "base_fine": 500, "source_clause": "Sec 177 MVA" },
  { "offense_code": "DL-139", "description": "Without uniform (Commercial drivers) (Sec 177 MVA)", "state_code": "NCT", "vehicle_class": "COMMERCIAL", "base_fine": 500, "source_clause": "Sec 177 MVA" },
  { "offense_code": "DL-140", "description": "Misbehavior with passenger (Commercial) (Sec 177 MVA)", "state_code": "NCT", "vehicle_class": "COMMERCIAL", "base_fine": 500, "source_clause": "Sec 177 MVA" },
  { "offense_code": "DL-141", "description": "Racing or trial of speed (Sec 189 MVA)", "state_code": "NCT", "vehicle_class": "*", "base_fine": 5000, "source_clause": "Sec 189 MVA" },
  { "offense_code": "DL-142", "description": "Using vehicle in unsafe condition (Sec 190(1) MVA)", "state_code": "NCT", "vehicle_class": "*", "base_fine": 1500, "source_clause": "Sec 190(1) MVA" },
  { "offense_code": "DL-143", "description": "Obstructing traffic (Sec 201 MVA)", "state_code": "NCT", "vehicle_class": "*", "base_fine": 500, "source_clause": "Sec 201 MVA" },
  { "offense_code": "DL-144", "description": "Driving left-hand drive vehicle without indicator (Sec 177 MVA)", "state_code": "NCT", "vehicle_class": "*", "base_fine": 500, "source_clause": "Sec 177 MVA" },
  { "offense_code": "DL-145", "description": "Failing to stop when involved in accident (Sec 132/177 MVA)", "state_code": "NCT", "vehicle_class": "*", "base_fine": 500, "source_clause": "Sec 132/177 MVA" },
  { "offense_code": "DL-146", "description": "Leaving vehicle in dangerous position (Sec 122/177 MVA)", "state_code": "NCT", "vehicle_class": "*", "base_fine": 500, "source_clause": "Sec 122/177 MVA" },
  { "offense_code": "DL-147", "description": "Riding on running board (Sec 123/177 MVA)", "state_code": "NCT", "vehicle_class": "*", "base_fine": 500, "source_clause": "Sec 123/177 MVA" },
  { "offense_code": "DL-148", "description": "Carrying person on bonnet (Sec 177 MVA)", "state_code": "NCT", "vehicle_class": "*", "base_fine": 500, "source_clause": "Sec 177 MVA" },
  { "offense_code": "DL-149", "description": "Driving reverse for undue distance (Sec 177 MVA)", "state_code": "NCT", "vehicle_class": "*", "base_fine": 500, "source_clause": "Sec 177 MVA" },
  { "offense_code": "DL-150", "description": "Not keeping to the left (Sec 177 MVA)", "state_code": "NCT", "vehicle_class": "*", "base_fine": 500, "source_clause": "Sec 177 MVA" },
  { "offense_code": "DL-151", "description": "Overtaking from wrong side (Sec 177 MVA)", "state_code": "NCT", "vehicle_class": "*", "base_fine": 500, "source_clause": "Sec 177 MVA" },
  { "offense_code": "DL-152", "description": "Taking U-turn where prohibited (Sec 177 MVA)", "state_code": "NCT", "vehicle_class": "*", "base_fine": 500, "source_clause": "Sec 177 MVA" },
  { "offense_code": "DL-153", "description": "Disobeying traffic sign (Sec 119/177 MVA)", "state_code": "NCT", "vehicle_class": "*", "base_fine": 500, "source_clause": "Sec 119/177 MVA" },
  { "offense_code": "DL-154", "description": "Crossing yellow line (Sec 177 MVA)", "state_code": "NCT", "vehicle_class": "*", "base_fine": 500, "source_clause": "Sec 177 MVA" },
  { "offense_code": "DL-155", "description": "Not yielding right of way to pedestrians at crossing (Sec 177 MVA)", "state_code": "NCT", "vehicle_class": "*", "base_fine": 500, "source_clause": "Sec 177 MVA" },
  { "offense_code": "DL-90", "description": "Riding two-wheeler without proper footwear / shoes / wearing slippers (Rule 90 DMVR & Sec 177 MVA)", "state_code": "NCT", "vehicle_class": "TWO_WHEELER", "base_fine": 1000, "source_clause": "Rule 90 DMVR" }
]
